src/__init__.py
src/aurai.py
aurask_ai-0.1.0.dist-info/METADATA
aurask_ai-0.1.0.dist-info/WHEEL
aurask_ai-0.1.0.dist-info/top_level.txt
aurask_ai-0.1.0.dist-info/RECORD
